odoo/addons/product_brand_tag/README.rst
odoo/addons/product_brand_tag/__init__.py
odoo/addons/product_brand_tag/__manifest__.py
odoo/addons/product_brand_tag/i18n/es.po
odoo/addons/product_brand_tag/i18n/it.po
odoo/addons/product_brand_tag/i18n/product_brand_tag.pot
odoo/addons/product_brand_tag/models/__init__.py
odoo/addons/product_brand_tag/models/product_brand.py
odoo/addons/product_brand_tag/models/product_brand_tag.py
odoo/addons/product_brand_tag/models/product_brand_tag_mixin.py
odoo/addons/product_brand_tag/readme/CONTRIBUTORS.md
odoo/addons/product_brand_tag/readme/DESCRIPTION.md
odoo/addons/product_brand_tag/security/ir.model.access.csv
odoo/addons/product_brand_tag/security/ir_rule.xml
odoo/addons/product_brand_tag/static/description/icon.png
odoo/addons/product_brand_tag/static/description/index.html
odoo/addons/product_brand_tag/tests/__init__.py
odoo/addons/product_brand_tag/tests/test_product_brand.py
odoo/addons/product_brand_tag/views/product_brand_tag_view.xml
odoo/addons/product_brand_tag/views/product_brand_view.xml
odoo_addon_product_brand_tag-18.0.1.0.0.2.dist-info/METADATA
odoo_addon_product_brand_tag-18.0.1.0.0.2.dist-info/WHEEL
odoo_addon_product_brand_tag-18.0.1.0.0.2.dist-info/top_level.txt
odoo_addon_product_brand_tag-18.0.1.0.0.2.dist-info/RECORD
